mongosql/__init__.py
mongosql/bag.py
mongosql/crud/__init__.py
mongosql/crud/crudhelper.py
mongosql/crud/crudview.py
mongosql/exc.py
mongosql/handlers/__init__.py
mongosql/handlers/aggregate.py
mongosql/handlers/base.py
mongosql/handlers/count.py
mongosql/handlers/filter.py
mongosql/handlers/group.py
mongosql/handlers/join.py
mongosql/handlers/joinf.py
mongosql/handlers/limit.py
mongosql/handlers/project.py
mongosql/handlers/sort.py
mongosql/query.py
mongosql/sa.py
mongosql/util/__init__.py
mongosql/util/bulk.py
mongosql/util/counting_query_wrapper.py
mongosql/util/history_proxy.py
mongosql/util/inspect.py
mongosql/util/marker.py
mongosql/util/method_decorator.py
mongosql/util/mongoquery_settings_handler.py
mongosql/util/reusable.py
mongosql/util/selectinquery.py
mongosql/util/settings_dict.py
mongosql-2.0.15.post1.dist-info/LICENSE
mongosql-2.0.15.post1.dist-info/WHEEL
mongosql-2.0.15.post1.dist-info/METADATA
mongosql-2.0.15.post1.dist-info/RECORD
