Metadata-Version: 2.1
Name: mongosql
Version: 2.0.15.post1
Summary: A JSON query engine with SqlAlchemy as a back-end
Home-page: https://github.com/kolypto/py-mongosql
Author: Mark Vartanyan
Author-email: kolypto@gmail.com
Requires-Python: >=3.6,<4.0
Classifier: Programming Language :: Python :: 3
Classifier: Programming Language :: Python :: 3.6
Classifier: Programming Language :: Python :: 3.7
Classifier: Programming Language :: Python :: 3.8
Classifier: Programming Language :: Python :: 3.9
Requires-Dist: nplus1loader (>=1.0,<2.0)
Requires-Dist: sqlalchemy (>=1.2,<2.0,!=1.2.9,<1.4)
Project-URL: Repository, https://github.com/kolypto/py-mongosql
